setup.py
Gamwo/__init__.py
Gamwo/entity.py
Gamwo/input.py
Gamwo/line.py
Gamwo/main.py
Gamwo/sprite.py
Gamwo.egg-info/PKG-INFO
Gamwo.egg-info/SOURCES.txt
Gamwo.egg-info/dependency_links.txt
Gamwo.egg-info/top_level.txt
gamwo/__init__.py
gamwo/entity.py
gamwo/fps.py
gamwo/input.py
gamwo/line.py
gamwo/main.py
gamwo/mixer.py
gamwo/sprite.py
gamwo/text.py
gamwo/timer.py
gamwo/vector2.py