Metadata-Version: 2.1
Name: Gamwo
Version: 0.1.2
Summary: Simple python framework for 2d games
Home-page: https://github.com/RinkaGI/Gamwo
Author: RinkaDev
Author-email: rinkadevoficial@gmail.com
License: MIT
Keywords: game,framework,2d,simple,pygame
Platform: UNKNOWN
